pyalsolver/__init__.py
pyalsolver/als.py
pyalsolver/py.typed
pyalsolver/utils/__init__.py
pyalsolver/utils/dataloader.py
pyalsolver/utils/plotter.py
pyalsolver-0.0.12.dist-info/METADATA
pyalsolver-0.0.12.dist-info/WHEEL
pyalsolver-0.0.12.dist-info/RECORD
