Metadata-Version: 2.3
Name: pyalsolver
Version: 0.0.12
Summary: A package for matrix factorization using alternating least squares
Project-URL: Repository, https://github.com/0xgeorgeassaad/ALSolver
Author-email: George Assaad <lopgogo@gmail.com>
Classifier: Intended Audience :: Developers
Classifier: Programming Language :: Python
Classifier: Programming Language :: Python :: 3 :: Only
Classifier: Programming Language :: Python :: 3.10
Classifier: Programming Language :: Python :: 3.11
Classifier: Programming Language :: Python :: 3.12
Classifier: Programming Language :: Python :: 3.13
Classifier: Topic :: Software Development :: Libraries
Requires-Python: >=3.10
Requires-Dist: matplotlib>=3.9.2
Requires-Dist: numba>=0.60.0
Requires-Dist: numpy==2.0.0
Requires-Dist: pandas>=2.2.3
Requires-Dist: requests>=2.32.3
Requires-Dist: scikit-learn>=1.5.2
Requires-Dist: scipy>=1.14.1
